q2db/__init__.py
q2db/cursor.py
q2db/db.py
q2db/schema.py
q2db/utils.py
q2db/version.py
q2db-0.1.62.dist-info/LICENSE
q2db-0.1.62.dist-info/METADATA
q2db-0.1.62.dist-info/WHEEL
q2db-0.1.62.dist-info/RECORD
