Metadata-Version: 2.1
Name: q2db
Version: 0.1.62
Summary: python DB API wrapper (MySQL, PostgreSQL, SQLite)
License: Apache 2.0
Author: Andrei Puchko
Author-email: andrei.puchko@gmx.de
Requires-Python: >=3.8.1
Classifier: License :: Other/Proprietary License
Classifier: Programming Language :: Python :: 3
Classifier: Programming Language :: Python :: 3.9
Classifier: Programming Language :: Python :: 3.10
Classifier: Programming Language :: Python :: 3.11
Requires-Dist: mysql-connector-python (>=8.0.29,<9.0.0)
Requires-Dist: psycopg2-binary (>=2.9.3,<3.0.0)
